[
  {
    "id": "choosing-the-right-solar-inverter-for-your-needs",
    "slug": "choosing-the-right-solar-inverter-for-your-needs",
    "title": "Choosing the Right Solar Inverter for Your Needs",
    "date": "June 20, 2024",
    "day": "20",
    "month": "June",
    "author": "Admin",
    "commentsCount": 2,
    "image": "/assets/images/blog_bifacial_panels.webp",
    "excerpt": "Learn about the critical aspects of selecting a solar inverter for your residential, commercial, or utility-scale project.",
    "template": "editorial",
    "tags": ["Solar", "Inverters", "Energy", "Technology"],
    "categories": ["Products", "Solar Inverter"],
    "blocks": [
      {
        "type": "paragraph",
        "text": "Choosing the right solar inverter is a crucial decision for your solar energy system. Inverters are the 'brain' of the solar project, responsible for converting the direct current (DC) electricity generated by solar panels into alternating current (AC) electricity used by home appliances and the grid."
      },
      {
        "type": "heading",
        "level": 2,
        "text": "Key Factors in Inverter Selection"
      },
      {
        "type": "paragraph",
        "text": "When selecting a solar inverter, key considerations include the capacity of your solar panel array, grid compatibility, efficiency ratings, temperature coefficient, and advanced monitoring systems."
      },
      {
        "type": "two_column",
        "left": [
          {
            "type": "heading",
            "level": 3,
            "text": "String Inverters"
          },
          {
            "type": "paragraph",
            "text": "Best suited for large rooftops with minimal shading. They offer high efficiency and lower cost per watt, making them the go-to choice for utility and commercial installations."
          }
        ],
        "right": [
          {
            "type": "heading",
            "level": 3,
            "text": "Microinverters"
          },
          {
            "type": "paragraph",
            "text": "Ideal for complex rooftops with shading or multiple orientations. Each panel operates independently, maximizing overall system yield even in partial shade conditions."
          }
        ]
      },
      {
        "type": "heading",
        "level": 2,
        "text": "SunLynk's Inverter Range"
      },
      {
        "type": "list",
        "style": "bullet",
        "items": [
          "Single-phase string inverters — 1kW to 10kW for homes",
          "Three-phase string inverters — 10kW to 250kW for commercial projects",
          "Hybrid inverters with built-in MPPT battery charging",
          "Utility-grade central inverters for MW-scale solar farms"
        ]
      },
      {
        "type": "image",
        "src": "/assets/images/blog_bifacial_panels.webp",
        "alt": "SunLynk Solar Inverter Range",
        "caption": "SunLynk distributes a complete range of bankable inverter solutions"
      }
    ],
    "comments": [
      {
        "author": "Layerdrops",
        "avatar": "/assets/images/blog/blog-comment-1-1.webp",
        "text": "Neque porro est qui dolorem ipsum quia dolor sit amet, consectetur, adipisci velit, sed quia non numquam eius modi tempora incidunt ut labore et dolore magnam aliquam quaerat voluptatem.",
        "createdAt": "2024-03-20T14:37:00Z"
      },
      {
        "author": "SolarExpert",
        "avatar": "/assets/images/blog/blog-comment-1-2.webp",
        "text": "Great breakdown of the technical points regarding temperature coefficients and inverter clipping parameters. Would love to see more on hybrid inverter sizing.",
        "createdAt": "2024-03-21T10:15:00Z"
      }
    ]
  },
  {
    "id": "why-class-a-weather-monitoring-is-essential-for-utility-pv",
    "slug": "why-class-a-weather-monitoring-is-essential-for-utility-pv",
    "title": "Why Class-A Weather Monitoring is Essential for Utility PV",
    "date": "April 28, 2026",
    "day": "28",
    "month": "Apr",
    "author": "SunLynk Editorial",
    "commentsCount": 0,
    "image": "/assets/images/blog_weather_station.webp",
    "excerpt": "Precise meteorological data is key to calculating performance ratio (PR). Discover why Class-A pyranometers and weather monitoring stations are required by grid operators.",
    "template": "magazine",
    "tags": ["Weather Monitoring", "SCADA", "Performance Ratio", "Utility PV"],
    "categories": ["Engineering", "Monitoring"],
    "blocks": [
      {
        "type": "paragraph",
        "text": "In a utility-scale solar plant, every percentage point of Performance Ratio (PR) directly translates to revenue. A PR of 79% vs 81% on a 100MW plant can mean hundreds of thousands of dollars in annual lost production. The accuracy of your irradiance measurements is the single largest non-engineering variable in this equation."
      },
      {
        "type": "heading",
        "level": 2,
        "text": "What Is a Class-A Pyranometer?"
      },
      {
        "type": "paragraph",
        "text": "The ISO 9060:2018 standard classifies pyranometers into Class A, B, and C based on their measurement uncertainty, directional response, and temperature dependence. Class-A instruments offer the highest accuracy with uncertainties below 2% — mandatory for grid operator reporting and lender technical due diligence."
      },
      {
        "type": "grid",
        "columns": 2,
        "items": [
          {
            "image": "/assets/images/blog_weather_station.webp",
            "caption": "Class-A Weather Station at a 50MW Solar Plant"
          },
          {
            "image": "/assets/images/blog_bifacial_panels.webp",
            "caption": "Bifacial Sensors for Rear Irradiance Measurement"
          }
        ]
      },
      {
        "type": "heading",
        "level": 2,
        "text": "IEC 61724-1 Compliance Requirements"
      },
      {
        "type": "list",
        "style": "ordered",
        "items": [
          "At minimum one Class-A pyranometer in the plane-of-array (POA)",
          "Ambient temperature sensor with ±0.5°C accuracy",
          "Module temperature sensor with ±1°C accuracy",
          "Wind speed and direction sensors",
          "Data logger with <1% measurement error and cellular/RS485 connectivity"
        ]
      },
      {
        "type": "two_column",
        "left": [
          {
            "type": "heading",
            "level": 3,
            "text": "For Lenders & Developers"
          },
          {
            "type": "paragraph",
            "text": "Financial lenders require at least 12 months of Class-A irradiance data for accurate P90 yield assessment. SunLynk's weather stations have been accepted by all major lenders for project bankability."
          }
        ],
        "right": [
          {
            "type": "heading",
            "level": 3,
            "text": "For O&M Teams"
          },
          {
            "type": "paragraph",
            "text": "Real-time soiling loss detection, shading analysis, and fault identification — SunLynk's SCADA dashboard integrates directly with Class-A sensors for live PR calculation."
          }
        ]
      }
    ],
    "comments": []
  },
  {
    "id": "integrating-battery-storage-bess-with-scada-for-grid-stability",
    "slug": "integrating-battery-storage-bess-with-scada-for-grid-stability",
    "title": "Integrating Battery Storage (BESS) with SCADA for Grid Stability",
    "date": "April 15, 2026",
    "day": "15",
    "month": "Apr",
    "author": "Tech Team",
    "commentsCount": 1,
    "image": "/assets/images/blog_battery_storage.webp",
    "excerpt": "Hybrid solar systems combining battery energy storage require intelligent SCADA dispatch algorithms. We analyze how Modbus control loops maintain zero-export grid compliance.",
    "template": "minimal",
    "tags": ["BESS", "SCADA", "Grid Stability", "Battery Storage", "Hybrid Solar"],
    "categories": ["Solutions", "Energy Storage", "Engineering"],
    "blocks": [
      {
        "type": "paragraph",
        "text": "As solar penetration in grid-tied systems increases, the challenge of managing surplus generation and peak demand becomes critical. Battery Energy Storage Systems (BESS) integrated via SCADA are emerging as the definitive solution to this challenge."
      },
      {
        "type": "heading",
        "level": 2,
        "text": "The Zero-Export Problem"
      },
      {
        "type": "paragraph",
        "text": "Many industrial and commercial consumers face zero-export requirements from their DISCOM — they can generate solar energy but cannot feed back to the grid. Without a BESS, this means curtailing solar generation during off-peak load periods. With BESS + SCADA, excess generation charges batteries instead of going to waste."
      },
      {
        "type": "image",
        "src": "/assets/images/blog_battery_storage.webp",
        "alt": "BESS integrated with a commercial solar installation",
        "caption": "A 500kWh BESS system integrated with SunLynk's SCADA at a manufacturing plant"
      },
      {
        "type": "heading",
        "level": 2,
        "text": "Modbus Control Loop Architecture"
      },
      {
        "type": "list",
        "style": "ordered",
        "items": [
          "Grid meter measures import/export in real time (±1% accuracy CT sensors)",
          "SCADA reads grid power via Modbus RTU/TCP at 1-second intervals",
          "Dispatch algorithm computes optimal charge/discharge setpoint",
          "BESS BMS receives setpoint via Modbus → executes in <500ms",
          "Solar inverter clipping is avoided by directing surplus to BESS first"
        ]
      },
      {
        "type": "two_column",
        "left": [
          {
            "type": "heading",
            "level": 3,
            "text": "Peak Shaving Mode"
          },
          {
            "type": "paragraph",
            "text": "SCADA identifies peak demand periods from historical load profiles. Battery discharges before the peak window to reduce maximum demand charges — one of the largest cost centers for commercial consumers."
          }
        ],
        "right": [
          {
            "type": "heading",
            "level": 3,
            "text": "Backup Power Mode"
          },
          {
            "type": "paragraph",
            "text": "During grid outages, the SCADA initiates island mode within 20ms. The BESS sustains critical loads while solar continues generating — providing seamless, uninterrupted power to your facility."
          }
        ]
      }
    ],
    "comments": [
      {
        "author": "GridEngineer",
        "avatar": "/assets/images/blog/blog-comment-1-1.webp",
        "text": "The Modbus dispatch latency figures here are very helpful. We're designing a 1MW/2MWh system and were unsure about the control loop timing requirements. This clears it up.",
        "createdAt": "2026-04-17T09:22:00Z"
      }
    ]
  }
]